Metadata-Version: 1.1
Name: topiary
Version: 3.0.6
Summary: Predict cancer epitopes from cancer sequence data
Home-page: https://github.com/hammerlab/topiary
Author: Alex Rubinsteyn, Tavi Nathanson
Author-email: alex.rubinsteyn@gmail.com
License: http://www.apache.org/licenses/LICENSE-2.0.html
Platform: UNKNOWN
Classifier: Development Status :: 3 - Alpha
Classifier: Environment :: Console
Classifier: Operating System :: OS Independent
Classifier: Intended Audience :: Science/Research
Classifier: License :: OSI Approved :: Apache Software License
Classifier: Programming Language :: Python
Classifier: Topic :: Scientific/Engineering :: Bio-Informatics
